README.md
setup.py
dtogen/__init__.py
dtogen/__main__.py
dtogen/dtogenerator.py
dtogen/interfaces.py
dtogen/run.py
dtogen.egg-info/PKG-INFO
dtogen.egg-info/SOURCES.txt
dtogen.egg-info/dependency_links.txt
dtogen.egg-info/requires.txt
dtogen.egg-info/top_level.txt
dtogen/filewriters/__init__.py
dtogen/filewriters/filewriter.py
dtogen/filewriters/filewriter_golang.py
dtogen/filewriters/filewriter_java.py
dtogen/filewriters/filewriter_python.py
dtogen/filewriters/filewriter_typescript.py
dtogen/transformers/__init__.py
dtogen/transformers/transformer.py
dtogen/transformers/transformer_golang.py
dtogen/transformers/transformer_java.py
dtogen/transformers/transformer_python.py
dtogen/transformers/transformer_typescript.py
test/test_dtogenerator.py
test/test_transform.py