Metadata-Version: 2.1
Name: dtogen
Version: 0.0.16
Summary: DTO generator for Java, TypeScript, Python
Home-page: https://github.com/mujdecisy/dtogen
Author: mujdecisy
Author-email: mujdecisy@gmail.com
Keywords: python,DTO,generator
Classifier: Programming Language :: Python :: 3
Requires-Dist: mapperr==0.2.4
Requires-Dist: pyyaml
